[
  {
    "name": "theme_info",
    "logo": "https://avatars2.githubusercontent.com/u/11925384?v=3&s=400",
    "settings": [
      {
        "type": "header",
        "content": "Alabama Blonde"
      }, {
        "type": "paragraph",
        "content": "v1.0"
      }, {
        "type": "paragraph",
        "content": "Custom shopify theme for AlabamaBlonde.com by -> xavier-burrow.com"
      }
    ]
  }, {
    "name": "Front Page",
    "settings": [{
      "type": "checkbox",
      "id": "disable_landing_page_video",
      "default": false,
      "label": "Disable Landing Page Video"
    }, {
      "type": "image_picker",
      "id": "index_featured_image",
      "label": "Featured Image",
      "info": "Suggested dimensions 1280 x 640 (2:1)"
    }, {
      "type": "url",
      "id": "index_featured_url",
      "label": "Feature Image URL"
    }, {
      "type": "textarea",
      "id": "index_about_text",
      "label": "Landing Page About Text"
    }, {
      "type": "image_picker",
      "id": "index_about_image",
      "label": "Landing Page About Image"
    }]
  }, {
    "name": "Promotional Bar",
    "settings":[
      {
        "type": "text",
        "id": "promo_label",
        "label": "Promotional bar text"
      },{
        "type": "text",
        "id": "promo_url",
        "label": "Promotional bar URL"
      }
    ]
  }, {
      "name": "About/ Brand Page",
      "settings": [
        {
          "type": "image_picker",
          "id": "about_page_image",
          "label": "About Page Banner Image"
        }, {
          "type": "image_picker",
          "id": "brand_page_image",
          "label": "Brand Page Banner Image"
        }
      ]
  }, {
    "name": "Cart page",
    "settings": [
      {
        "type": "checkbox",
        "id": "cart_notes_enable",
        "label": "Enable cart notes"
      },
      {
        "type": "checkbox",
        "id": "cart_vendor_enable",
        "label": "Show product vendor"
      },
      {
        "type": "select",
        "id": "ajax_cart_method",
        "label": "Cart type",
        "options": [
          {
            "value": "drawer",
            "label": "Drawer"
          },
          {
            "value": "page",
            "label": "Page"
          }
        ]
      }
    ]
  }, {
    "name": "Social media",
    "settings": [{
        "type": "checkbox",
        "id": "enable_instagram_feed",
        "label": "Enable Instagram Feed"
      }, {
        "type": "text",
        "id": "social_twitter_link",
        "label": "Twitter URL",
        "info": "https:\/\/twitter.com\/shopify"
      }, {
        "type": "text",
        "id": "social_facebook_link",
        "label": "Facebook URL",
        "info": "https:\/\/www.facebook.com\/shopify"
      }, {
        "type": "text",
        "id": "social_instagram_link",
        "label": "Instagram URL",
        "info": "https:\/\/instagram.com\/shopify"
      }, {
        "type": "text",
        "id": "social_pinterest_link",
        "label": "Pinterest URL",
        "info": "https:\/\/pinterest.com\/shopify"
      }
    ]
  }
]
